langchain_pinecone-0.2.10.dist-info/METADATA
langchain_pinecone-0.2.10.dist-info/WHEEL
langchain_pinecone-0.2.10.dist-info/entry_points.txt
langchain_pinecone-0.2.10.dist-info/licenses/LICENSE
langchain_pinecone/__init__.py
langchain_pinecone/_utilities.py
langchain_pinecone/embeddings.py
langchain_pinecone/py.typed
langchain_pinecone/rerank.py
langchain_pinecone/vectorstores.py
langchain_pinecone/vectorstores_sparse.py
langchain_pinecone-0.2.10.dist-info/RECORD
