Metadata-Version: 2.1
Name: langchain-pinecone
Version: 0.2.10
Summary: An integration package connecting Pinecone and LangChain
License: MIT
Project-URL: Source Code, https://github.com/langchain-ai/langchain-pinecone/tree/main/libs/pinecone
Project-URL: Release Notes, https://github.com/langchain-ai/langchain/releases?q=tag%3A%22langchain-pinecone%3D%3D0%22&expanded=true
Project-URL: repository, https://github.com/langchain-ai/langchain-pinecone
Requires-Python: <3.14,>=3.9
Requires-Dist: langchain-core<1.0.0,>=0.3.34
Requires-Dist: pinecone[asyncio]<8.0.0,>=6.0.0
Requires-Dist: numpy>=1.26.4
Requires-Dist: langchain-tests<1.0.0,>=0.3.7
Requires-Dist: langchain-openai>=0.3.11
